{"err_code":"EC0000000","err_message":"APPROVED/OK","result":{"points":[{"updateTime":1671069699728,"from_time":1671069602326,"from_price":50,"to_price":50,"low":50,"high":50,"tradable_volume_start":100,"tradable_volume_end":11200,"volume":11100},{"updateTime":1671070661233,"from_time":1671070200000,"from_price":50,"to_price":50,"low":50,"high":50,"tradable_volume_start":11200,"tradable_volume_end":31500,"volume":20300},{"updateTime":1671071314703,"from_time":1671070800000,"from_price":50,"to_price":50,"low":50,"high":50,"tradable_volume_start":31500,"tradable_volume_end":31900,"volume":400},{"updateTime":1671072287440,"from_time":1671072000000,"from_price":50,"to_price":50,"low":50,"high":50,"tradable_volume_start":31900,"tradable_volume_end":32500,"volume":600},{"updateTime":1671072794531,"from_time":1671072600000,"from_price":50,"to_price":50,"low":50,"high":50,"tradable_volume_start":32500,"tradable_volume_end":37300,"volume":4800},{"updateTime":1671073434438,"from_time":1671073200000,"from_price":50,"to_price":50,"low":50,"high":50,"tradable_volume_start":37300,"tradable_volume_end":38300,"volume":1000},{"updateTime":1671074830488,"from_time":1671074400000,"from_price":50,"to_price":50,"low":50,"high":50,"tradable_volume_start":38300,"tradable_volume_end":58400,"volume":20100},{"updateTime":1671075501766,"from_time":1671075000000,"from_price":50,"to_price":50,"low":50,"high":50,"tradable_volume_start":58400,"tradable_volume_end":64400,"volume":6000},{"updateTime":1671077300551,"from_time":1671076800000,"from_price":50,"to_price":50,"low":50,"high":50,"tradable_volume_start":64400,"tradable_volume_end":69400,"volume":5000},{"updateTime":1671078315499,"from_time":1671078000000,"from_price":50,"to_price":50,"low":50,"high":50,"tradable_volume_start":69400,"tradable_volume_end":69900,"volume":500},{"updateTime":1671086211382,"from_time":1671085800000,"from_price":50,"to_price":50,"low":50,"high":50,"tradable_volume_start":69900,"tradable_volume_end":103500,"volume":33600},{"updateTime":1671088770767,"from_time":1671088200000,"from_price":50,"to_price":50,"low":50,"high":50,"tradable_volume_start":103500,"tradable_volume_end":103600,"volume":100},{"updateTime":1671089762942,"from_time":1671089400000,"from_price":50,"to_price":50,"low":50,"high":50,"tradable_volume_start":103600,"tradable_volume_end":105200,"volume":1600},{"updateTime":1671091358054,"from_time":1671091200000,"from_price":50,"to_price":50,"low":50,"high":50,"tradable_volume_start":105200,"tradable_volume_end":105500,"volume":300},{"updateTime":1671156378139,"from_time":1671156000000,"from_price":50,"to_price":50,"low":50,"high":50,"tradable_volume_start":105500,"tradable_volume_end":300,"volume":-105200},{"updateTime":1671157156314,"from_time":1671156600000,"from_price":50,"to_price":50,"low":50,"high":50,"tradable_volume_start":300,"tradable_volume_end":2700,"volume":2400},{"updateTime":1671157679572,"from_time":1671157200000,"from_price":50,"to_price":50,"low":50,"high":50,"tradable_volume_start":2700,"tradable_volume_end":3800,"volume":1100},{"updateTime":1671158222978,"from_time":1671157800000,"from_price":50,"to_price":50,"low":50,"high":50,"tradable_volume_start":3800,"tradable_volume_end":5800,"volume":2000},{"updateTime":1671160351929,"from_time":1671160200000,"from_price":50,"to_price":50,"low":50,"high":50,"tradable_volume_start":5800,"tradable_volume_end":35800,"volume":30000},{"updateTime":1671161587636,"from_time":1671161400000,"from_price":50,"to_price":50,"low":50,"high":50,"tradable_volume_start":35800,"tradable_volume_end":36100,"volume":300},{"updateTime":1671162455012,"from_time":1671162000000,"from_price":50,"to_price":50,"low":50,"high":50,"tradable_volume_start":36100,"tradable_volume_end":40100,"volume":4000},{"updateTime":1671163693760,"from_time":1671163200000,"from_price":50,"to_price":50,"low":50,"high":50,"tradable_volume_start":40100,"tradable_volume_end":40500,"volume":400},{"updateTime":1671163861558,"from_time":1671163800000,"from_price":50,"to_price":50,"low":50,"high":50,"tradable_volume_start":40500,"tradable_volume_end":41600,"volume":1100},{"updateTime":1671172203957,"from_time":1671172200000,"from_price":50,"to_price":50,"low":50,"high":50,"tradable_volume_start":41600,"tradable_volume_end":43600,"volume":2000},{"updateTime":1671173197940,"from_time":1671172800000,"from_price":50,"to_price":50,"low":50,"high":50,"tradable_volume_start":43600,"tradable_volume_end":43700,"volume":100},{"updateTime":1671174074053,"from_time":1671174000000,"from_price":50,"to_price":50,"low":50,"high":50,"tradable_volume_start":43700,"tradable_volume_end":43800,"volume":100},{"updateTime":1671175230546,"from_time":1671175200000,"from_price":50,"to_price":50,"low":50,"high":50,"tradable_volume_start":43800,"tradable_volume_end":43900,"volume":100},{"updateTime":1671177603392,"from_time":1671177600000,"from_price":50,"to_price":50,"low":50,"high":50,"tradable_volume_start":43900,"tradable_volume_end":44200,"volume":300},{"updateTime":1671178216757,"from_time":1671178200000,"from_price":50,"to_price":50,"low":50,"high":50,"tradable_volume_start":44200,"tradable_volume_end":44300,"volume":100}]},"count":0}