{"err_code":"EC0000000","err_message":"APPROVED/OK","result":{"points":[{"updateTime":1664852330628,"from_time":1664848805450,"from_price":173,"to_price":173,"low":172,"high":176,"tradable_volume_start":200,"tradable_volume_end":851700,"volume":851500},{"updateTime":1664855994027,"from_time":1664852400000,"from_price":173,"to_price":174,"low":173,"high":175,"tradable_volume_start":851700,"tradable_volume_end":1098900,"volume":247200},{"updateTime":1664857743538,"from_time":1664856000000,"from_price":174,"to_price":175,"low":174,"high":175,"tradable_volume_start":1098900,"tradable_volume_end":1420300,"volume":321400},{"updateTime":1664866728847,"from_time":1664863200000,"from_price":175,"to_price":175,"low":174,"high":176,"tradable_volume_start":1420300,"tradable_volume_end":2247200,"volume":826900},{"updateTime":1664869792975,"from_time":1664866800000,"from_price":175,"to_price":179,"low":175,"high":180,"tradable_volume_start":2247200,"tradable_volume_end":7142800,"volume":4895600},{"updateTime":1664871281441,"from_time":1664870400000,"from_price":179,"to_price":182,"low":179,"high":182,"tradable_volume_start":7142800,"tradable_volume_end":9698200,"volume":2555400},{"updateTime":1664938729943,"from_time":1664935200000,"from_price":182,"to_price":178,"low":176,"high":183,"tradable_volume_start":9698200,"tradable_volume_end":5581100,"volume":-4117100},{"updateTime":1664940004994,"from_time":1664938800000,"from_price":178,"to_price":178,"low":178,"high":179,"tradable_volume_start":5581100,"tradable_volume_end":5777900,"volume":196800}]},"count":0}