{"err_code":"EC0000000","err_message":"APPROVED/OK","result":{"points":[{"updateTime":1666839560213,"from_time":1666836001667,"from_price":119,"to_price":120,"low":119,"high":122,"tradable_volume_start":1000,"tradable_volume_end":4201300,"volume":4200300},{"updateTime":1666843198555,"from_time":1666839600000,"from_price":120,"to_price":120,"low":119,"high":120,"tradable_volume_start":4201300,"tradable_volume_end":5670900,"volume":1469600},{"updateTime":1666844977681,"from_time":1666843200000,"from_price":120,"to_price":121,"low":119,"high":122,"tradable_volume_start":5670900,"tradable_volume_end":7414600,"volume":1743700},{"updateTime":1666853986379,"from_time":1666850400000,"from_price":121,"to_price":124,"low":120,"high":129,"tradable_volume_start":7414600,"tradable_volume_end":49530900,"volume":42116300},{"updateTime":1666856998900,"from_time":1666854000000,"from_price":124,"to_price":124,"low":123,"high":127,"tradable_volume_start":49530900,"tradable_volume_end":62468800,"volume":12937900},{"updateTime":1666858427029,"from_time":1666857600000,"from_price":124,"to_price":125,"low":124,"high":125,"tradable_volume_start":62468800,"tradable_volume_end":66252900,"volume":3784100},{"updateTime":1666925976051,"from_time":1666922400000,"from_price":125,"to_price":122,"low":121,"high":127,"tradable_volume_start":66252900,"tradable_volume_end":21512500,"volume":-44740400},{"updateTime":1666928143281,"from_time":1666926000000,"from_price":122,"to_price":119,"low":118,"high":122,"tradable_volume_start":21512500,"tradable_volume_end":34662300,"volume":13149800}]},"count":0}