{"err_code":"EC0000000","err_message":"APPROVED/OK","result":{"points":[{"updateTime":1671072963362,"from_time":1671070116625,"from_price":530,"to_price":530,"low":530,"high":535,"tradable_volume_start":500,"tradable_volume_end":19300,"volume":18800},{"updateTime":1671075713984,"from_time":1671073200000,"from_price":530,"to_price":525,"low":525,"high":530,"tradable_volume_start":19300,"tradable_volume_end":42400,"volume":23100},{"updateTime":1671078213687,"from_time":1671076800000,"from_price":525,"to_price":520,"low":520,"high":525,"tradable_volume_start":42400,"tradable_volume_end":112400,"volume":70000},{"updateTime":1671086762232,"from_time":1671084000000,"from_price":520,"to_price":520,"low":520,"high":525,"tradable_volume_start":112400,"tradable_volume_end":131500,"volume":19100},{"updateTime":1671090488434,"from_time":1671087600000,"from_price":520,"to_price":520,"low":520,"high":520,"tradable_volume_start":131500,"tradable_volume_end":225100,"volume":93600},{"updateTime":1671091790500,"from_time":1671091200000,"from_price":520,"to_price":520,"low":520,"high":520,"tradable_volume_start":225100,"tradable_volume_end":245100,"volume":20000},{"updateTime":1671157881488,"from_time":1671156000000,"from_price":520,"to_price":520,"low":520,"high":525,"tradable_volume_start":245100,"tradable_volume_end":110800,"volume":-134300},{"updateTime":1671162589489,"from_time":1671159600000,"from_price":520,"to_price":525,"low":520,"high":525,"tradable_volume_start":110800,"tradable_volume_end":197300,"volume":86500},{"updateTime":1671164182924,"from_time":1671163200000,"from_price":525,"to_price":530,"low":525,"high":530,"tradable_volume_start":197300,"tradable_volume_end":198500,"volume":1200},{"updateTime":1671173451756,"from_time":1671170400000,"from_price":530,"to_price":520,"low":520,"high":530,"tradable_volume_start":198500,"tradable_volume_end":198700,"volume":200},{"updateTime":1671176914982,"from_time":1671174000000,"from_price":520,"to_price":515,"low":515,"high":520,"tradable_volume_start":198700,"tradable_volume_end":300000,"volume":101300},{"updateTime":1671177604956,"from_time":1671177600000,"from_price":515,"to_price":520,"low":515,"high":520,"tradable_volume_start":300000,"tradable_volume_end":303000,"volume":3000}]},"count":0}