{"err_code":"EC0000000","err_message":"APPROVED/OK","result":{"points":[{"updateTime":1671071144281,"from_time":1671071144281,"from_price":545,"to_price":545,"low":545,"high":545,"tradable_volume_start":100,"tradable_volume_end":100,"volume":0},{"updateTime":1671091205389,"from_time":1671091200000,"from_price":545,"to_price":585,"low":545,"high":585,"tradable_volume_start":100,"tradable_volume_end":300,"volume":200},{"updateTime":1671156579494,"from_time":1671156000000,"from_price":585,"to_price":585,"low":585,"high":585,"tradable_volume_start":300,"tradable_volume_end":100,"volume":-200}]},"count":0}