{"err_code":"EC0000000","err_message":"APPROVED/OK","result":{"points":[{"updateTime":1664762699784,"from_time":1664762400216,"from_price":137,"to_price":137,"low":135,"high":137,"tradable_volume_start":349900,"tradable_volume_end":60604000,"volume":60254100},{"updateTime":1664762999731,"from_time":1664762700000,"from_price":137,"to_price":135,"low":135,"high":137,"tradable_volume_start":60604000,"tradable_volume_end":144906100,"volume":84302100},{"updateTime":1664763299782,"from_time":1664763000000,"from_price":135,"to_price":136,"low":135,"high":136,"tradable_volume_start":144906100,"tradable_volume_end":179431600,"volume":34525500},{"updateTime":1664763599018,"from_time":1664763300000,"from_price":136,"to_price":139,"low":136,"high":139,"tradable_volume_start":179431600,"tradable_volume_end":316761200,"volume":137329600},{"updateTime":1664763896705,"from_time":1664763600000,"from_price":139,"to_price":139,"low":137,"high":140,"tradable_volume_start":316761200,"tradable_volume_end":849276800,"volume":532515600},{"updateTime":1664764197294,"from_time":1664763900000,"from_price":139,"to_price":138,"low":137,"high":139,"tradable_volume_start":849276800,"tradable_volume_end":955270000,"volume":105993200},{"updateTime":1664764497254,"from_time":1664764200000,"from_price":138,"to_price":139,"low":137,"high":139,"tradable_volume_start":955270000,"tradable_volume_end":970548700,"volume":15278700},{"updateTime":1664764796850,"from_time":1664764500000,"from_price":139,"to_price":139,"low":138,"high":139,"tradable_volume_start":970548700,"tradable_volume_end":997571700,"volume":27023000},{"updateTime":1664765097176,"from_time":1664764800000,"from_price":139,"to_price":137,"low":137,"high":139,"tradable_volume_start":997571700,"tradable_volume_end":1194254400,"volume":196682700},{"updateTime":1664765370470,"from_time":1664765100000,"from_price":137,"to_price":138,"low":137,"high":138,"tradable_volume_start":1194254400,"tradable_volume_end":1209726700,"volume":15472300}]},"count":0}