{"err_code":"EC0000000","err_message":"APPROVED/OK","result":{"points":[{"updateTime":1665972293205,"from_time":1665972007699,"from_price":8700,"to_price":8650,"low":8650,"high":8700,"tradable_volume_start":9900,"tradable_volume_end":56100,"volume":46200},{"updateTime":1665972585357,"from_time":1665972300000,"from_price":8650,"to_price":8625,"low":8600,"high":8650,"tradable_volume_start":56100,"tradable_volume_end":360800,"volume":304700},{"updateTime":1665972891726,"from_time":1665972600000,"from_price":8625,"to_price":8625,"low":8625,"high":8650,"tradable_volume_start":360800,"tradable_volume_end":375700,"volume":14900},{"updateTime":1665973189880,"from_time":1665972900000,"from_price":8625,"to_price":8625,"low":8625,"high":8650,"tradable_volume_start":375700,"tradable_volume_end":450000,"volume":74300},{"updateTime":1665973488556,"from_time":1665973200000,"from_price":8625,"to_price":8600,"low":8600,"high":8650,"tradable_volume_start":450000,"tradable_volume_end":547900,"volume":97900},{"updateTime":1665973708995,"from_time":1665973500000,"from_price":8600,"to_price":8625,"low":8600,"high":8625,"tradable_volume_start":547900,"tradable_volume_end":550000,"volume":2100},{"updateTime":1665974084556,"from_time":1665973800000,"from_price":8625,"to_price":8600,"low":8600,"high":8625,"tradable_volume_start":550000,"tradable_volume_end":559300,"volume":9300},{"updateTime":1665974388675,"from_time":1665974100000,"from_price":8600,"to_price":8625,"low":8600,"high":8650,"tradable_volume_start":559300,"tradable_volume_end":722600,"volume":163300},{"updateTime":1665974691669,"from_time":1665974400000,"from_price":8625,"to_price":8625,"low":8600,"high":8650,"tradable_volume_start":722600,"tradable_volume_end":754100,"volume":31500},{"updateTime":1665974985827,"from_time":1665974700000,"from_price":8625,"to_price":8625,"low":8600,"high":8625,"tradable_volume_start":754100,"tradable_volume_end":785900,"volume":31800},{"updateTime":1665975293519,"from_time":1665975000000,"from_price":8625,"to_price":8600,"low":8600,"high":8625,"tradable_volume_start":785900,"tradable_volume_end":882100,"volume":96200},{"updateTime":1665975569939,"from_time":1665975300000,"from_price":8600,"to_price":8625,"low":8600,"high":8625,"tradable_volume_start":882100,"tradable_volume_end":890600,"volume":8500},{"updateTime":1665975891190,"from_time":1665975600000,"from_price":8625,"to_price":8625,"low":8600,"high":8625,"tradable_volume_start":890600,"tradable_volume_end":894700,"volume":4100},{"updateTime":1665976147563,"from_time":1665975900000,"from_price":8625,"to_price":8625,"low":8600,"high":8625,"tradable_volume_start":894700,"tradable_volume_end":918700,"volume":24000},{"updateTime":1665976491043,"from_time":1665976200000,"from_price":8625,"to_price":8625,"low":8600,"high":8625,"tradable_volume_start":918700,"tradable_volume_end":933200,"volume":14500},{"updateTime":1665976777932,"from_time":1665976500000,"from_price":8625,"to_price":8625,"low":8600,"high":8650,"tradable_volume_start":933200,"tradable_volume_end":1094500,"volume":161300},{"updateTime":1665977085259,"from_time":1665976800000,"from_price":8625,"to_price":8625,"low":8600,"high":8625,"tradable_volume_start":1094500,"tradable_volume_end":1100700,"volume":6200},{"updateTime":1665977378376,"from_time":1665977100000,"from_price":8625,"to_price":8600,"low":8575,"high":8625,"tradable_volume_start":1100700,"tradable_volume_end":1267300,"volume":166600},{"updateTime":1665977694542,"from_time":1665977400000,"from_price":8600,"to_price":8600,"low":8575,"high":8600,"tradable_volume_start":1267300,"tradable_volume_end":1289100,"volume":21800},{"updateTime":1665977965275,"from_time":1665977700000,"from_price":8600,"to_price":8575,"low":8575,"high":8600,"tradable_volume_start":1289100,"tradable_volume_end":1299200,"volume":10100},{"updateTime":1665978141705,"from_time":1665978000000,"from_price":8575,"to_price":8600,"low":8575,"high":8600,"tradable_volume_start":1299200,"tradable_volume_end":1305000,"volume":5800}]},"count":0}